Ai_security_platform.py
ai_security_platform-1.0.dist-info/licenses/LICENSE.txt
ai_security_platform-1.0.dist-info/METADATA
ai_security_platform-1.0.dist-info/WHEEL
ai_security_platform-1.0.dist-info/top_level.txt
ai_security_platform-1.0.dist-info/RECORD
