Metadata-Version: 2.4
Name: Ai_security_platform
Version: 1.0
Summary: RAG
Author-email: user <user@gmail.com>
License: MIT
Project-URL: Homepage, https://github.com
Requires-Python: >=3.8
License-File: LICENSE.txt
Dynamic: license-file
